fractal_tictactoe_analyzer/__init__.py
fractal_tictactoe_analyzer/main.py
fractal_tictactoe_analyzer/prompts.py
fractal_tictactoe_analyzer-2025.12.21131323.dist-info/METADATA
fractal_tictactoe_analyzer-2025.12.21131323.dist-info/WHEEL
fractal_tictactoe_analyzer-2025.12.21131323.dist-info/top_level.txt
fractal_tictactoe_analyzer-2025.12.21131323.dist-info/RECORD
