Metadata-Version: 2.4
Name: fractal-tictactoe-analyzer
Version: 2025.12.21131323
Summary: A new package that processes user descriptions of fractal TicTacToe game states or strategies and returns structured analysis, such as identifying optimal moves, detecting winning patterns, or suggest
Author-email: fractal-tictactoe-analyzer <hi@eugene.plus>
License: MIT
Project-URL: Homepage, https://github.com/chigwell/fractal-tictactoe-analyzer
Requires-Python: >=3.9
Requires-Dist: langchain-llm7>=0.0.0
Requires-Dist: llmatch-messages>=0.0.0
Requires-Dist: langchain-core>=0.3.0
